<annotation>
  <folder>LP</folder>
  <filename>102227245_P_T04</filename>
  <path>D:\2.SAT_LPR_DATA\T04_not_done\LP\102227245_P_T04.jpg</path>
  <source>
    <database>Unknown</database>
  </source>
  <size>
    <width>205</width>
    <height>78</height>
    <depth>1</depth>
  </size>
  <segmented>0</segmented>
  <object>
    <name>&#51064;&#52380;_V</name>
    <pose>Unspecified</pose>
    <truncated>0</truncated>
    <difficult>0</difficult>
    <bndbox>
      <xmin>19</xmin>
      <ymin>14</ymin>
      <xmax>38</xmax>
      <ymax>46</ymax>
    </bndbox>
  </object>
  <object>
    <name>9</name>
    <pose>Unspecified</pose>
    <truncated>0</truncated>
    <difficult>0</difficult>
    <bndbox>
      <xmin>39</xmin>
      <ymin>16</ymin>
      <xmax>56</xmax>
      <ymax>46</ymax>
    </bndbox>
  </object>
  <object>
    <name>9</name>
    <pose>Unspecified</pose>
    <truncated>0</truncated>
    <difficult>0</difficult>
    <bndbox>
      <xmin>59</xmin>
      <ymin>18</ymin>
      <xmax>76</xmax>
      <ymax>47</ymax>
    </bndbox>
  </object>
  <object>
    <name>&#50500;</name>
    <pose>Unspecified</pose>
    <truncated>0</truncated>
    <difficult>0</difficult>
    <bndbox>
      <xmin>77</xmin>
      <ymin>22</ymin>
      <xmax>98</xmax>
      <ymax>48</ymax>
    </bndbox>
  </object>
  <object>
    <name>4</name>
    <pose>Unspecified</pose>
    <truncated>0</truncated>
    <difficult>0</difficult>
    <bndbox>
      <xmin>103</xmin>
      <ymin>22</ymin>
      <xmax>123</xmax>
      <ymax>53</ymax>
    </bndbox>
  </object>
  <object>
    <name>5</name>
    <pose>Unspecified</pose>
    <truncated>0</truncated>
    <difficult>0</difficult>
    <bndbox>
      <xmin>125</xmin>
      <ymin>24</ymin>
      <xmax>144</xmax>
      <ymax>55</ymax>
    </bndbox>
  </object>
  <object>
    <name>7</name>
    <pose>Unspecified</pose>
    <truncated>0</truncated>
    <difficult>0</difficult>
    <bndbox>
      <xmin>144</xmin>
      <ymin>25</ymin>
      <xmax>163</xmax>
      <ymax>57</ymax>
    </bndbox>
  </object>
  <object>
    <name>5</name>
    <pose>Unspecified</pose>
    <truncated>0</truncated>
    <difficult>0</difficult>
    <bndbox>
      <xmin>166</xmin>
      <ymin>27</ymin>
      <xmax>184</xmax>
      <ymax>58</ymax>
    </bndbox>
  </object>
</annotation>
