<annotation>
  <folder>LP</folder>
  <filename>17703011605300640001657_P_T18</filename>
  <path>D:\ALBA\SAT_LPR_DATA_2\T18_not_done\LP\17703011605300640001657_P_T18.jpg</path>
  <source>
    <database>Unknown</database>
  </source>
  <size>
    <width>229</width>
    <height>127</height>
    <depth>1</depth>
  </size>
  <segmented>0</segmented>
  <object>
    <name>&#44221;&#44592;_O</name>
    <pose>Unspecified</pose>
    <truncated>0</truncated>
    <difficult>0</difficult>
    <bndbox>
      <xmin>65</xmin>
      <ymin>11</ymin>
      <xmax>119</xmax>
      <ymax>40</ymax>
    </bndbox>
  </object>
  <object>
    <name>6</name>
    <pose>Unspecified</pose>
    <truncated>0</truncated>
    <difficult>0</difficult>
    <bndbox>
      <xmin>121</xmin>
      <ymin>14</ymin>
      <xmax>143</xmax>
      <ymax>44</ymax>
    </bndbox>
  </object>
  <object>
    <name>5</name>
    <pose>Unspecified</pose>
    <truncated>0</truncated>
    <difficult>0</difficult>
    <bndbox>
      <xmin>146</xmin>
      <ymin>15</ymin>
      <xmax>169</xmax>
      <ymax>46</ymax>
    </bndbox>
  </object>
  <object>
    <name>&#47336;</name>
    <pose>Unspecified</pose>
    <truncated>0</truncated>
    <difficult>0</difficult>
    <bndbox>
      <xmin>12</xmin>
      <ymin>43</ymin>
      <xmax>55</xmax>
      <ymax>87</ymax>
    </bndbox>
  </object>
  <object>
    <name>6</name>
    <pose>Unspecified</pose>
    <truncated>0</truncated>
    <difficult>0</difficult>
    <bndbox>
      <xmin>69</xmin>
      <ymin>47</ymin>
      <xmax>103</xmax>
      <ymax>112</ymax>
    </bndbox>
  </object>
  <object>
    <name>4</name>
    <pose>Unspecified</pose>
    <truncated>0</truncated>
    <difficult>0</difficult>
    <bndbox>
      <xmin>107</xmin>
      <ymin>50</ymin>
      <xmax>140</xmax>
      <ymax>114</ymax>
    </bndbox>
  </object>
  <object>
    <name>5</name>
    <pose>Unspecified</pose>
    <truncated>0</truncated>
    <difficult>0</difficult>
    <bndbox>
      <xmin>144</xmin>
      <ymin>50</ymin>
      <xmax>180</xmax>
      <ymax>117</ymax>
    </bndbox>
  </object>
  <object>
    <name>0</name>
    <pose>Unspecified</pose>
    <truncated>0</truncated>
    <difficult>0</difficult>
    <bndbox>
      <xmin>182</xmin>
      <ymin>53</ymin>
      <xmax>219</xmax>
      <ymax>119</ymax>
    </bndbox>
  </object>
</annotation>
