<annotation>
  <folder>LP_T17_not_done</folder>
  <filename>17703021605301418043037_P_T17</filename>
  <path>D:\SAT_LPR_DATA_2\LP_T17_not_done\17703021605301418043037_P_T17.jpg</path>
  <source>
    <database>Unknown</database>
  </source>
  <size>
    <width>233</width>
    <height>138</height>
    <depth>1</depth>
  </size>
  <segmented>0</segmented>
  <object>
    <name>0</name>
    <pose>Unspecified</pose>
    <truncated>0</truncated>
    <difficult>0</difficult>
    <bndbox>
      <xmin>64</xmin>
      <ymin>12</ymin>
      <xmax>96</xmax>
      <ymax>41</ymax>
    </bndbox>
  </object>
  <object>
    <name>4</name>
    <pose>Unspecified</pose>
    <truncated>0</truncated>
    <difficult>0</difficult>
    <bndbox>
      <xmin>101</xmin>
      <ymin>15</ymin>
      <xmax>133</xmax>
      <ymax>44</ymax>
    </bndbox>
  </object>
  <object>
    <name>&#45908;</name>
    <pose>Unspecified</pose>
    <truncated>0</truncated>
    <difficult>0</difficult>
    <bndbox>
      <xmin>137</xmin>
      <ymin>17</ymin>
      <xmax>171</xmax>
      <ymax>46</ymax>
    </bndbox>
  </object>
  <object>
    <name>4</name>
    <pose>Unspecified</pose>
    <truncated>0</truncated>
    <difficult>0</difficult>
    <bndbox>
      <xmin>14</xmin>
      <ymin>45</ymin>
      <xmax>60</xmax>
      <ymax>112</ymax>
    </bndbox>
  </object>
  <object>
    <name>5</name>
    <pose>Unspecified</pose>
    <truncated>0</truncated>
    <difficult>0</difficult>
    <bndbox>
      <xmin>68</xmin>
      <ymin>47</ymin>
      <xmax>114</xmax>
      <ymax>114</ymax>
    </bndbox>
  </object>
  <object>
    <name>5</name>
    <pose>Unspecified</pose>
    <truncated>0</truncated>
    <difficult>0</difficult>
    <bndbox>
      <xmin>121</xmin>
      <ymin>52</ymin>
      <xmax>168</xmax>
      <ymax>119</ymax>
    </bndbox>
  </object>
  <object>
    <name>0</name>
    <pose>Unspecified</pose>
    <truncated>0</truncated>
    <difficult>0</difficult>
    <bndbox>
      <xmin>174</xmin>
      <ymin>54</ymin>
      <xmax>222</xmax>
      <ymax>122</ymax>
    </bndbox>
  </object>
</annotation>
