<annotation>
  <folder>LP</folder>
  <filename>20180416101605000_P_T05</filename>
  <path>D:\ALBA\2.SAT_LPR_DATA\T05_not_done\LP\20180416101605000_P_T05.jpg</path>
  <source>
    <database>Unknown</database>
  </source>
  <size>
    <width>269</width>
    <height>136</height>
    <depth>1</depth>
  </size>
  <segmented>0</segmented>
  <object>
    <name>9</name>
    <pose>Unspecified</pose>
    <truncated>0</truncated>
    <difficult>0</difficult>
    <bndbox>
      <xmin>16</xmin>
      <ymin>46</ymin>
      <xmax>47</xmax>
      <ymax>106</ymax>
    </bndbox>
  </object>
  <object>
    <name>1</name>
    <pose>Unspecified</pose>
    <truncated>0</truncated>
    <difficult>0</difficult>
    <bndbox>
      <xmin>50</xmin>
      <ymin>45</ymin>
      <xmax>80</xmax>
      <ymax>105</ymax>
    </bndbox>
  </object>
  <object>
    <name>&#45908;</name>
    <pose>Unspecified</pose>
    <truncated>0</truncated>
    <difficult>0</difficult>
    <bndbox>
      <xmin>83</xmin>
      <ymin>56</ymin>
      <xmax>115</xmax>
      <ymax>104</ymax>
    </bndbox>
  </object>
  <object>
    <name>7</name>
    <pose>Unspecified</pose>
    <truncated>0</truncated>
    <difficult>0</difficult>
    <bndbox>
      <xmin>118</xmin>
      <ymin>44</ymin>
      <xmax>149</xmax>
      <ymax>104</ymax>
    </bndbox>
  </object>
  <object>
    <name>9</name>
    <pose>Unspecified</pose>
    <truncated>0</truncated>
    <difficult>0</difficult>
    <bndbox>
      <xmin>152</xmin>
      <ymin>42</ymin>
      <xmax>184</xmax>
      <ymax>104</ymax>
    </bndbox>
  </object>
  <object>
    <name>6</name>
    <pose>Unspecified</pose>
    <truncated>0</truncated>
    <difficult>0</difficult>
    <bndbox>
      <xmin>186</xmin>
      <ymin>42</ymin>
      <xmax>219</xmax>
      <ymax>102</ymax>
    </bndbox>
  </object>
  <object>
    <name>3</name>
    <pose>Unspecified</pose>
    <truncated>0</truncated>
    <difficult>0</difficult>
    <bndbox>
      <xmin>220</xmin>
      <ymin>42</ymin>
      <xmax>250</xmax>
      <ymax>100</ymax>
    </bndbox>
  </object>
</annotation>
