<annotation>
  <folder>LP</folder>
  <filename>20180517153826000_P_T05</filename>
  <path>D:\SAT_LPR_DATA_2\T05_not_done\LP\20180517153826000_P_T05.jpg</path>
  <source>
    <database>Unknown</database>
  </source>
  <size>
    <width>243</width>
    <height>135</height>
    <depth>1</depth>
  </size>
  <segmented>0</segmented>
  <object>
    <name>8</name>
    <pose>Unspecified</pose>
    <truncated>0</truncated>
    <difficult>0</difficult>
    <bndbox>
      <xmin>14</xmin>
      <ymin>42</ymin>
      <xmax>41</xmax>
      <ymax>98</ymax>
    </bndbox>
  </object>
  <object>
    <name>4</name>
    <pose>Unspecified</pose>
    <truncated>0</truncated>
    <difficult>0</difficult>
    <bndbox>
      <xmin>43</xmin>
      <ymin>44</ymin>
      <xmax>71</xmax>
      <ymax>100</ymax>
    </bndbox>
  </object>
  <object>
    <name>&#49688;</name>
    <pose>Unspecified</pose>
    <truncated>0</truncated>
    <difficult>0</difficult>
    <bndbox>
      <xmin>74</xmin>
      <ymin>55</ymin>
      <xmax>101</xmax>
      <ymax>101</ymax>
    </bndbox>
  </object>
  <object>
    <name>7</name>
    <pose>Unspecified</pose>
    <truncated>0</truncated>
    <difficult>0</difficult>
    <bndbox>
      <xmin>107</xmin>
      <ymin>47</ymin>
      <xmax>133</xmax>
      <ymax>103</ymax>
    </bndbox>
  </object>
  <object>
    <name>6</name>
    <pose>Unspecified</pose>
    <truncated>0</truncated>
    <difficult>0</difficult>
    <bndbox>
      <xmin>137</xmin>
      <ymin>47</ymin>
      <xmax>165</xmax>
      <ymax>104</ymax>
    </bndbox>
  </object>
  <object>
    <name>0</name>
    <pose>Unspecified</pose>
    <truncated>0</truncated>
    <difficult>0</difficult>
    <bndbox>
      <xmin>168</xmin>
      <ymin>48</ymin>
      <xmax>194</xmax>
      <ymax>106</ymax>
    </bndbox>
  </object>
  <object>
    <name>7</name>
    <pose>Unspecified</pose>
    <truncated>0</truncated>
    <difficult>0</difficult>
    <bndbox>
      <xmin>199</xmin>
      <ymin>49</ymin>
      <xmax>226</xmax>
      <ymax>106</ymax>
    </bndbox>
  </object>
</annotation>
