<annotation>
  <folder>T04_LP_not_done_2</folder>
  <filename>20180420144558000_P_T04</filename>
  <path>D:\SAT_LPR_DATA_2\T04_LP_not_done_2\20180420144558000_P_T04.jpg</path>
  <source>
    <database>Unknown</database>
  </source>
  <size>
    <width>278</width>
    <height>76</height>
    <depth>1</depth>
  </size>
  <segmented>0</segmented>
  <object>
    <name>&#48512;&#49328;_V</name>
    <pose>Unspecified</pose>
    <truncated>0</truncated>
    <difficult>0</difficult>
    <bndbox>
      <xmin>21</xmin>
      <ymin>13</ymin>
      <xmax>46</xmax>
      <ymax>57</ymax>
    </bndbox>
  </object>
  <object>
    <name>9</name>
    <pose>Unspecified</pose>
    <truncated>0</truncated>
    <difficult>0</difficult>
    <bndbox>
      <xmin>49</xmin>
      <ymin>14</ymin>
      <xmax>72</xmax>
      <ymax>57</ymax>
    </bndbox>
  </object>
  <object>
    <name>9</name>
    <pose>Unspecified</pose>
    <truncated>0</truncated>
    <difficult>0</difficult>
    <bndbox>
      <xmin>76</xmin>
      <ymin>15</ymin>
      <xmax>100</xmax>
      <ymax>59</ymax>
    </bndbox>
  </object>
  <object>
    <name>&#49324;</name>
    <pose>Unspecified</pose>
    <truncated>0</truncated>
    <difficult>0</difficult>
    <bndbox>
      <xmin>106</xmin>
      <ymin>19</ymin>
      <xmax>131</xmax>
      <ymax>57</ymax>
    </bndbox>
  </object>
  <object>
    <name>6</name>
    <pose>Unspecified</pose>
    <truncated>0</truncated>
    <difficult>0</difficult>
    <bndbox>
      <xmin>143</xmin>
      <ymin>18</ymin>
      <xmax>169</xmax>
      <ymax>63</ymax>
    </bndbox>
  </object>
  <object>
    <name>7</name>
    <pose>Unspecified</pose>
    <truncated>0</truncated>
    <difficult>0</difficult>
    <bndbox>
      <xmin>170</xmin>
      <ymin>18</ymin>
      <xmax>195</xmax>
      <ymax>62</ymax>
    </bndbox>
  </object>
  <object>
    <name>5</name>
    <pose>Unspecified</pose>
    <truncated>0</truncated>
    <difficult>0</difficult>
    <bndbox>
      <xmin>202</xmin>
      <ymin>19</ymin>
      <xmax>227</xmax>
      <ymax>64</ymax>
    </bndbox>
  </object>
  <object>
    <name>9</name>
    <pose>Unspecified</pose>
    <truncated>0</truncated>
    <difficult>0</difficult>
    <bndbox>
      <xmin>229</xmin>
      <ymin>19</ymin>
      <xmax>255</xmax>
      <ymax>64</ymax>
    </bndbox>
  </object>
</annotation>
